vopy/__init__.py
vopy/confidence_region.py
vopy/design_space.py
vopy/maximization_problem.py
vopy/order.py
vopy/ordering_cone.py
vopy/version.py
vopy/acquisition/__init__.py
vopy/acquisition/acquisition.py
vopy/algorithms/__init__.py
vopy/algorithms/algorithm.py
vopy/algorithms/auer.py
vopy/algorithms/decoupled.py
vopy/algorithms/epal.py
vopy/algorithms/naive_elimination.py
vopy/algorithms/paveba.py
vopy/algorithms/paveba_gp.py
vopy/algorithms/paveba_gp_online.py
vopy/algorithms/paveba_partial_gp.py
vopy/algorithms/vogp.py
vopy/algorithms/vogp_ad.py
vopy/datasets/__init__.py
vopy/datasets/dataset.py
vopy/datasets/data/VehicleSafety.npy
vopy/datasets/data/brake.npy
vopy/datasets/data/fairness.npy
vopy/datasets/data/sort_256.csv
vopy/datasets/data/test.npy
vopy/models/__init__.py
vopy/models/empirical_mean_var.py
vopy/models/gpytorch.py
vopy/models/kernels.py
vopy/models/model.py
vopy/utils/__init__.py
vopy/utils/evaluate.py
vopy/utils/plotting.py
vopy/utils/seed.py
vopy/utils/transforms.py
vopy/utils/utils.py
vopy-0.1.4.dist-info/licenses/LICENSE
vopy-0.1.4.dist-info/METADATA
vopy-0.1.4.dist-info/WHEEL
vopy-0.1.4.dist-info/top_level.txt
vopy-0.1.4.dist-info/RECORD
