Metadata-Version: 2.4
Name: VOPy
Version: 0.1.4
Summary: A framework for black-box vector optimization
Author-email: "Y. Cahit Yıldırım" <cahit.yildirim@bilkent.edu.tr>
License: MIT License
Project-URL: Homepage, https://github.com/Bilkent-CYBORG/VOPy
Project-URL: Documentation, https://vopy.readthedocs.io/en/latest/
Project-URL: Issues, https://github.com/Bilkent-CYBORG/VOPy/issues
Requires-Python: >=3.10
License-File: LICENSE
Requires-Dist: botorch<0.12.0,>=0.10.0
Requires-Dist: cvxpy
Requires-Dist: scikit-learn
Requires-Dist: scipy
Requires-Dist: matplotlib
Provides-Extra: dev
Requires-Dist: black; extra == "dev"
Requires-Dist: usort; extra == "dev"
Requires-Dist: flake8; extra == "dev"
Requires-Dist: flake8-print; extra == "dev"
Provides-Extra: test
Requires-Dist: pre-commit; extra == "test"
Requires-Dist: pytest; extra == "test"
Requires-Dist: pytest-xdist; extra == "test"
Requires-Dist: pytest-cov; extra == "test"
Requires-Dist: bandit; extra == "test"
Provides-Extra: examples
Requires-Dist: jupyter; extra == "examples"
Requires-Dist: optuna; extra == "examples"
Provides-Extra: docs
Requires-Dist: pydocstyle; extra == "docs"
Requires-Dist: sphinx_rtd_theme; extra == "docs"
Requires-Dist: sphinx-notfound-page; extra == "docs"
Requires-Dist: nbsphinx; extra == "docs"
Dynamic: license-file
